LICENSE
README.md
setup.cfg
setup.py
biszx_pylint_odoo/__init__.py
biszx_pylint_odoo/settings.py
biszx_pylint_odoo.egg-info/PKG-INFO
biszx_pylint_odoo.egg-info/SOURCES.txt
biszx_pylint_odoo.egg-info/dependency_links.txt
biszx_pylint_odoo.egg-info/requires.txt
biszx_pylint_odoo.egg-info/top_level.txt
biszx_pylint_odoo/checker/__init__.py
biszx_pylint_odoo/checker/base_checker.py
biszx_pylint_odoo/checker/field_checker.py
biszx_pylint_odoo/checker/function_checker.py
biszx_pylint_odoo/messages/__init__.py
biszx_pylint_odoo/messages/field_checker_msg.py
biszx_pylint_odoo/messages/function_checker_msg.py
biszx_pylint_odoo/tests/__init__.py
biszx_pylint_odoo/tests/settings.py
biszx_pylint_odoo/tests/test_field_checker.py
biszx_pylint_odoo/tests/test_function_checker.py
biszx_pylint_odoo/tests/utils.py