Metadata-Version: 2.1
Name: biszx-pylint-odoo
Version: 2.0.4
Summary: Biszx Pylint plugin for Odoo
Home-page: https://gitlab.com/is4res/biszx-pylint-odoo
Author: Biszx
Author-email: isares.br@gmail.com
License: MIT
Classifier: Environment :: Console
Classifier: Intended Audience :: Developers
Classifier: Intended Audience :: Information Technology
Classifier: Operating System :: POSIX :: Linux
Classifier: Programming Language :: Python
License-File: LICENSE
